xganalyzer/__init__.py
xganalyzer/events_aggregator.py
xganalyzer/final_aggregator.py
xganalyzer/season_aggregator.py
xganalyzer-0.1.11.dist-info/LICENSE
xganalyzer-0.1.11.dist-info/METADATA
xganalyzer-0.1.11.dist-info/WHEEL
xganalyzer-0.1.11.dist-info/top_level.txt
xganalyzer-0.1.11.dist-info/RECORD
