Metadata-Version: 2.1
Name: xganalyzer
Version: 0.1.11
Summary: Package for xG statistics aggregation
Home-page: https://github.com/oRastor/xganalyzer
Author: Orest Bduzhak
Author-email: doom4eg@gmail.com
License: MIT
Keywords: football soccer xg expected-goals aggregation
License-File: LICENSE
Requires-Dist: pandas (~=1.3.5)
Requires-Dist: numpy (>=1.22.0)
Provides-Extra: dev
Requires-Dist: pytest ; extra == 'dev'
Requires-Dist: requests-mock ; extra == 'dev'
Requires-Dist: coverage ; extra == 'dev'
Requires-Dist: mypy ; extra == 'dev'
